py_unified_parser/.DS_Store
py_unified_parser/Config.py
py_unified_parser/IndicWord.py
py_unified_parser/LangSupport.py
py_unified_parser/Utils.py
py_unified_parser/Word.py
py_unified_parser/__init__.py
py_unified_parser/constants.py
py_unified_parser/dict/ENGLISH.dict
py_unified_parser/dict/English.EngHndCommon.dict
py_unified_parser/dict/HINDI.dict
py_unified_parser/dict/MALAYALAM.dict
py_unified_parser/final-release.version
py_unified_parser/rules/HINDI.rules
py_unified_parser/rules/KANNADA.rules
py_unified_parser/rules/MALAYALAM.rules
py_unified_parser/rules/TAMIL.rules
py_unified_parser/rules/TELUGU.rules
py_unified_parser/tsylb2-1.1/DISCLAIM.txt
py_unified_parser/tsylb2-1.1/INSTALL
py_unified_parser/tsylb2-1.1/Makefile
py_unified_parser/tsylb2-1.1/Makefile.in
py_unified_parser/tsylb2-1.1/README
py_unified_parser/tsylb2-1.1/addfwarn.c
py_unified_parser/tsylb2-1.1/addpcd.c
py_unified_parser/tsylb2-1.1/addstres.c
py_unified_parser/tsylb2-1.1/adjcase.c
py_unified_parser/tsylb2-1.1/aprules1.c
py_unified_parser/tsylb2-1.1/atobool.c
py_unified_parser/tsylb2-1.1/badicc1.c
py_unified_parser/tsylb2-1.1/booldef.h
py_unified_parser/tsylb2-1.1/boolpr1.c
py_unified_parser/tsylb2-1.1/calloc2.c
py_unified_parser/tsylb2-1.1/config.cache
py_unified_parser/tsylb2-1.1/config.log
py_unified_parser/tsylb2-1.1/config.status
py_unified_parser/tsylb2-1.1/configure
py_unified_parser/tsylb2-1.1/configure.in
py_unified_parser/tsylb2-1.1/csrates1.c
py_unified_parser/tsylb2-1.1/dbpkg1.c
py_unified_parser/tsylb2-1.1/decode2.c
py_unified_parser/tsylb2-1.1/del_eol.c
py_unified_parser/tsylb2-1.1/delchars.c
py_unified_parser/tsylb2-1.1/dhpars1.c
py_unified_parser/tsylb2-1.1/doc/algorithm.doc
py_unified_parser/tsylb2-1.1/doc/tsylb2.1
py_unified_parser/tsylb2-1.1/dpcode3.c
py_unified_parser/tsylb2-1.1/dpron2.c
py_unified_parser/tsylb2-1.1/dsylbs1.c
py_unified_parser/tsylb2-1.1/dwords1.c
py_unified_parser/tsylb2-1.1/enclcs1.c
py_unified_parser/tsylb2-1.1/encode2.c
py_unified_parser-1.0.0.dist-info/WHEEL
py_unified_parser-1.0.0.dist-info/METADATA
py_unified_parser-1.0.0.dist-info/RECORD
