Metadata-Version: 2.1
Name: py-unified-parser
Version: 1.0.0
Summary: 
License: Proprietary
Author: Arun Baby
Requires-Python: >=3.8,<3.10
Classifier: License :: Other/Proprietary License
Classifier: Programming Language :: Python :: 3
Classifier: Programming Language :: Python :: 3.8
Classifier: Programming Language :: Python :: 3.9
Requires-Dist: g2p-en (>=2.0.0,<3.0.0)
Requires-Dist: numpy (>=1.14,<2.0)
Requires-Dist: packaging (>=20.9,<21.0)
